core/__audio.py
core/__datetime.py
core/__init__.py
core/__json.py
core/__numbers.py
core/__path.py
core/__random.py
core/__selenium.py
core/__winapi.py
core/__zip.py
core/aesthetics.py
core/algorithm.py
core/animations.py
core/backtracking.py
core/development.py
core/download.py
core/drive.py
core/exceptions.py
core/image.py
core/pdf.py
core/romania.py
core/session.py
core/statistics.py
core/symbols.py
core/system.py
core/weather.py
core/__collections/BinaryTree.py
core/__collections/BlockChain.py
core/__collections/LinkedList.py
core/__collections/__init__.py
core/__collections/queue.py
core/__collections/stack.py
core/__collections/__dict/__dict.py
core/__collections/__dict/__init__.py
core/__collections/__dict/exceptions.py
core/__collections/__list/__init__.py
core/__collections/__list/__list.py
core/__collections/__list/exceptions.py
core/__collections/graph/__init__.py
core/__collections/graph/edges.json
core/__collections/graph/exceptions.py
core/__collections/graph/graph.py
core/gui/ColorsWindow.py
core/gui/__init__.py
core/gui/configs.py
core/gui/objects.py
core/sounds/__init__.py
core/sounds/autogen.py
core/sounds/initialize.py
core/sounds/paths.py
core/sounds/play.py
core/sounds/update.py
core/sounds/cs16/original/arcade.wav
core/sounds/cs16/original/break.wav
core/sounds/cs16/original/davai.wav
core/sounds/cs16/original/dominating.wav
core/sounds/cs16/original/doublekill.wav
core/sounds/cs16/original/eagleeye.wav
core/sounds/cs16/original/excellent.wav
core/sounds/cs16/original/explosion.wav
core/sounds/cs16/original/firstblood.wav
core/sounds/cs16/original/flawless.wav
core/sounds/cs16/original/godlike.wav
core/sounds/cs16/original/hattrick.wav
core/sounds/cs16/original/headhunter.wav
core/sounds/cs16/original/headshot.wav
core/sounds/cs16/original/here-comes-the-money.wav
core/sounds/cs16/original/holyshit.wav
core/sounds/cs16/original/humiliating-defeat.wav
core/sounds/cs16/original/humiliating.wav
core/sounds/cs16/original/humiliation.wav
python_core-0.1.2.dist-info/LICENSE
python_core-0.1.2.dist-info/METADATA
python_core-0.1.2.dist-info/WHEEL
python_core-0.1.2.dist-info/top_level.txt
python_core-0.1.2.dist-info/RECORD
