Metadata-Version: 2.1
Name: python-core
Version: 0.1.2
Summary: UNKNOWN
Home-page: UNKNOWN
Author: alexzander
Author-email: just.python.mail.test@gmail.com
License: UNKNOWN
Platform: any
Classifier: Programming Language :: Python :: 3
Classifier: License :: OSI Approved :: MIT License
Classifier: Operating System :: OS Independent
Requires-Python: >=3.7
Requires-Dist: aiohttp
Requires-Dist: altgraph
Requires-Dist: appdirs
Requires-Dist: argon2-cffi
Requires-Dist: args
Requires-Dist: asgiref
Requires-Dist: astroid
Requires-Dist: async-timeout
Requires-Dist: attrs
Requires-Dist: autopep8
Requires-Dist: backcall
Requires-Dist: beautifulsoup4
Requires-Dist: bitly-api
Requires-Dist: bleach
Requires-Dist: bs4
Requires-Dist: cachetools
Requires-Dist: cairocffi
Requires-Dist: CairoSVG
Requires-Dist: certifi
Requires-Dist: cffi
Requires-Dist: chardet
Requires-Dist: click
Requires-Dist: clint
Requires-Dist: colorama
Requires-Dist: colored-traceback
Requires-Dist: comtypes
Requires-Dist: cssselect
Requires-Dist: cssselect2
Requires-Dist: datedelta
Requires-Dist: decorator
Requires-Dist: defusedxml
Requires-Dist: Django
Requires-Dist: docutils
Requires-Dist: entrypoints
Requires-Dist: fake-useragent
Requires-Dist: ffmpeg-python
Requires-Dist: future
Requires-Dist: geojson
Requires-Dist: googletrans
Requires-Dist: gTTS
Requires-Dist: h11
Requires-Dist: h2
Requires-Dist: hpack
Requires-Dist: hstspreload
Requires-Dist: httpcore
Requires-Dist: httpx
Requires-Dist: hyperframe
Requires-Dist: idna
Requires-Dist: imageio
Requires-Dist: imageio-ffmpeg
Requires-Dist: importlib-metadata
Requires-Dist: InstagramAPI
Requires-Dist: ipinfo
Requires-Dist: ipykernel
Requires-Dist: ipython
Requires-Dist: ipython-genutils
Requires-Dist: ipywidgets
Requires-Dist: isort
Requires-Dist: jedi
Requires-Dist: Jinja2
Requires-Dist: jsonschema
Requires-Dist: jupyter-client
Requires-Dist: jupyter-console
Requires-Dist: jupyter-core
Requires-Dist: keyboard
Requires-Dist: keyring
Requires-Dist: Kivy
Requires-Dist: kivy-deps.angle
Requires-Dist: kivy-deps.glew
Requires-Dist: kivy-deps.gstreamer
Requires-Dist: kivy-deps.sdl2
Requires-Dist: Kivy-examples
Requires-Dist: Kivy-Garden
Requires-Dist: lazy-object-proxy
Requires-Dist: lxml
Requires-Dist: MarkupSafe
Requires-Dist: mccabe
Requires-Dist: mistune
Requires-Dist: MouseInfo
Requires-Dist: moviepy
Requires-Dist: multidict
Requires-Dist: mysqlclient
Requires-Dist: nbconvert
Requires-Dist: nbformat
Requires-Dist: notebook
Requires-Dist: numpy
Requires-Dist: opencv-python
Requires-Dist: packaging
Requires-Dist: pandocfilters
Requires-Dist: parse
Requires-Dist: parso
Requires-Dist: pdfminer.six
Requires-Dist: pdfplumber
Requires-Dist: pefile
Requires-Dist: pickleshare
Requires-Dist: Pillow
Requires-Dist: pkginfo
Requires-Dist: playsound
Requires-Dist: proglog
Requires-Dist: prometheus-client
Requires-Dist: prompt-toolkit
Requires-Dist: psutil
Requires-Dist: PyAudio
Requires-Dist: PyAutoGUI
Requires-Dist: pycodestyle
Requires-Dist: pycparser
Requires-Dist: pycryptodome
Requires-Dist: pydub
Requires-Dist: pyee
Requires-Dist: pygal
Requires-Dist: pygame
Requires-Dist: PyGetWindow
Requires-Dist: Pygments
Requires-Dist: pygubu
Requires-Dist: pygubu-designer
Requires-Dist: pyinstaller
Requires-Dist: pyinstaller-hooks-contrib
Requires-Dist: pylint
Requires-Dist: PyMsgBox
Requires-Dist: pynput
Requires-Dist: pyowm
Requires-Dist: pyparsing
Requires-Dist: PyPDF2
Requires-Dist: pyperclip
Requires-Dist: pypiwin32
Requires-Dist: pyppeteer
Requires-Dist: PyQt5
Requires-Dist: PyQt5-sip
Requires-Dist: pyquery
Requires-Dist: PyRect
Requires-Dist: pyrsistent
Requires-Dist: PyScreeze
Requires-Dist: PySocks
Requires-Dist: pytesseract
Requires-Dist: python-core
Requires-Dist: python-dateutil
Requires-Dist: pyttsx3
Requires-Dist: PyTweening
Requires-Dist: pytz
Requires-Dist: pywin32
Requires-Dist: pywin32-ctypes
Requires-Dist: pywinpty
Requires-Dist: pyzbar
Requires-Dist: pyzmq
Requires-Dist: qtconsole
Requires-Dist: QtPy
Requires-Dist: readme-renderer
Requires-Dist: requests
Requires-Dist: requests-html
Requires-Dist: requests-toolbelt
Requires-Dist: rfc3986
Requires-Dist: scipy
Requires-Dist: selenium
Requires-Dist: Send2Trash
Requires-Dist: six
Requires-Dist: sniffio
Requires-Dist: sortedcontainers
Requires-Dist: SoundCard
Requires-Dist: sounddevice
Requires-Dist: soupsieve
Requires-Dist: SpeechRecognition
Requires-Dist: spotipy
Requires-Dist: sqlparse
Requires-Dist: terminado
Requires-Dist: testpath
Requires-Dist: tinycss2
Requires-Dist: toml
Requires-Dist: tornado
Requires-Dist: tqdm
Requires-Dist: traitlets
Requires-Dist: twine
Requires-Dist: typed-ast
Requires-Dist: typing-extensions
Requires-Dist: urllib3
Requires-Dist: vboxapi
Requires-Dist: w3lib
Requires-Dist: Wand
Requires-Dist: wcwidth
Requires-Dist: webencodings
Requires-Dist: websockets
Requires-Dist: widgetsnbextension
Requires-Dist: win10toast
Requires-Dist: windows-curses
Requires-Dist: wrapt
Requires-Dist: yarl
Requires-Dist: zipp
